dino_perceptual/__init__.py
dino_perceptual/perceptual.py
dino_perceptual-0.1.3.dist-info/METADATA
dino_perceptual-0.1.3.dist-info/WHEEL
dino_perceptual-0.1.3.dist-info/top_level.txt
dino_perceptual-0.1.3.dist-info/RECORD
