Metadata-Version: 2.4
Name: dino-perceptual
Version: 0.1.3
Summary: DINO-based perceptual loss for image reconstruction and generation
Author: Philippe Hansen-Estruch, Jiahui Chen, Vivek Ramanujan, Orr Zohar, Yan Ping, Animesh Sinha, Markos Georgopoulos, Edgar Schoenfeld, Ji Hou, Felix Juefei-Xu, Sriram Vishwanath, Ali Thabet
License-Expression: MIT
Project-URL: Homepage, https://github.com/Na-VAE/dino-perceptual
Project-URL: Repository, https://github.com/Na-VAE/dino-perceptual
Keywords: deep-learning,perceptual-loss,dino,lpips,computer-vision,image-generation
Classifier: Development Status :: 4 - Beta
Classifier: Intended Audience :: Science/Research
Classifier: Programming Language :: Python :: 3
Classifier: Programming Language :: Python :: 3.10
Classifier: Programming Language :: Python :: 3.11
Classifier: Programming Language :: Python :: 3.12
Classifier: Topic :: Scientific/Engineering :: Artificial Intelligence
Requires-Python: >=3.10
Requires-Dist: torch>=2.0.0
Requires-Dist: transformers>=4.30.0
Provides-Extra: dev
Requires-Dist: pytest>=7.0; extra == "dev"
Requires-Dist: ruff>=0.1.0; extra == "dev"
Provides-Extra: examples
Requires-Dist: matplotlib>=3.5.0; extra == "examples"
Requires-Dist: pillow>=9.0.0; extra == "examples"
Requires-Dist: lpips>=0.1.4; extra == "examples"
